pyfiretvremote/__init__.py
pyfiretvremote/const.py
pyfiretvremote/firetvremote.py
pyfiretvremote/pair.py
pyfiretvremote-0.6.0.dist-info/WHEEL
pyfiretvremote-0.6.0.dist-info/entry_points.txt
pyfiretvremote-0.6.0.dist-info/METADATA
pyfiretvremote-0.6.0.dist-info/RECORD
