Metadata-Version: 2.3
Name: pyfiretvremote
Version: 0.6.0
Summary: Fire TV Remote Library
Requires-Dist: httpx>=0.28.1
Requires-Python: >=3.12
Project-URL: Homepage, https://github.com/designer-living/pyfiretvremote
Project-URL: Issues, https://github.com/designer-living/pyfiretvremote/issues
Project-URL: Repository, https://github.com/designer-living/pyfiretvremote
